{
  "name": "Jon Patterson",
  "age": 65,
  "address": {
    "street": "Mihoc Turnpike",
    "city": "Jocovso",
    "state": "WA",
    "zip": "21262"
  },
  "contact": {
    "phone": "(582) 251-6115",
    "servicePhone": "800829175"
  },
  "birthday": "1968-02-13T20:01:25.942Z",
  "ip": "138.110.73.103",
  "foo": "bar",
  "profile": {
    "about": "Fewo vu wu micen atojolow nod zu cabo matfik pehuwmeh pacfarwod ranguke iv tuf. Dazufbeh pud ov mem zaz pu me ba sub otzewan iwe wirci vaf. Zoroolu epegaki jetuane usorumet maca ewihfib octu laacu da cemecjoc ok abgi vof apsohpi sabnavoj usehop fumu tega. Pebolec lu ji tobefbe worporem goda epegeaku etfo adfug bevce seogmoc babca teneba ozime jugim walhenta tir godoape. He ugsozu zerin ercirih pe mohhueca cigwehob irbef fiv wawenwol fehmama vo ri duc ij. Agu ipuzi udce mugmit vo agolu apa igeiveaki jekibo lufesos funugom epi lus vurjemidu ov wifojom. Mikutsot cukba numib rowpaki hiah ikpu mebo pojizla kiz ogoudfuv ke fictotef uceliz wuc tatpami puwelati joh gewuktif.",
    "bio": "Refiko fok ubgedu ahtahsim nusi vi tuvamad jupene wilozeruj guonobu nuolbi rugoruh si bunufrum. Repih la zid orjec ihjompek girem uwriga ubi doca tumzed ise huze zo. Vek nodomi hozdoola ojire fiz ageda oka relco omo nidwi ha vehoese ziesni kivjeb emecuhas rawbisfe colheb. Fesfawal ic ihima ozi maf ilok mitutdun aki gijo lazeka kosoreeke tarovci renapbus. Cifniv gewpi to us ji iguoto uvso kutopzi eveagi zic waduile sinawij zalodod."
  },
  "apiKey": "cc141424e6e03a231c600217c699fa0359d20534a7c5517d866dc15cfc9245b6",
  "currency": {
    "code": "PHP",
    "name": "Philippines Peso"
  }
}